mtcli_atr/__init__.py
mtcli_atr/conf.py
mtcli_atr/controllers/__init__.py
mtcli_atr/controllers/atr_controller.py
mtcli_atr/models/__init__.py
mtcli_atr/models/atr_model.py
mtcli_atr/plugin.py
mtcli_atr/views/__init__.py
mtcli_atr/views/atr_view.py
mtcli_atr-1.2.1.dist-info/entry_points.txt
mtcli_atr-1.2.1.dist-info/LICENSE
mtcli_atr-1.2.1.dist-info/METADATA
mtcli_atr-1.2.1.dist-info/WHEEL
mtcli_atr-1.2.1.dist-info/RECORD
