Metadata-Version: 2.3
Name: mtcli-atr
Version: 1.2.1
Summary: Plugin mtcli do indicador ATR
License: GPL-3.0
Author: Valmir França da Silva
Author-email: vfranca3@gmail.com
Requires-Python: >=3.10,<3.14.0
Classifier: License :: OSI Approved :: GNU General Public License v3 (GPLv3)
Classifier: Programming Language :: Python :: 3
Classifier: Programming Language :: Python :: 3.10
Classifier: Programming Language :: Python :: 3.11
Classifier: Programming Language :: Python :: 3.12
Classifier: Programming Language :: Python :: 3.13
Requires-Dist: mtcli (>=1.18.1)
Project-URL: Documentation, https://mtcli-atr.readthedocs.io
Project-URL: Homepage, https://pypi.org/project/mtcli-atr
Project-URL: Repository, https://github.com/vfranca/mtcli-atr
Project-URL: issues, https://github.com/vfranca/mtcli-atr/issues
